zephyr_uploader/__init__.py
zephyr_uploader/__main__.py
zephyr_uploader/cli_constants.py
zephyr_uploader/env_loader.py
zephyr_uploader/environment.py
zephyr_uploader/execution_status.py
zephyr_uploader/exit_constants.py
zephyr_uploader/io_utils.py
zephyr_uploader/test_status.py
zephyr_uploader/zephyr_configurer.py
zephyr_uploader/zephyr_service.py
zephyr_uploader/zephyr_uploader.py
zephyr_uploader-1.0.3.dist-info/LICENSE
zephyr_uploader-1.0.3.dist-info/METADATA
zephyr_uploader-1.0.3.dist-info/WHEEL
zephyr_uploader-1.0.3.dist-info/top_level.txt
zephyr_uploader-1.0.3.dist-info/RECORD
