Metadata-Version: 2.1
Name: zephyr-uploader
Version: 1.0.3
Summary: Upload test execution results to Jira Zephyr. The input is an Excel document.
Home-page: https://github.com/estuaryoss/test-libs-python/tree/master/zephyr_uploader
Author: Catalin Dinuta
Author-email: constantin.dinuta@gmail.com
License: UNKNOWN
Platform: UNKNOWN
Classifier: Programming Language :: Python :: 3.7
Classifier: Programming Language :: Python :: 3.8
Classifier: Programming Language :: Python :: 3.9
Classifier: License :: OSI Approved :: Apache Software License
Classifier: Operating System :: OS Independent
Requires-Dist: click
Requires-Dist: pyexcel
Requires-Dist: requests
